lbftd/__init__.py
lbftd/evalGibbs.py
lbftd/loadGibbs.py
lbftd/statevars.py
mlbspline/__init__.py
mlbspline/eval.py
mlbspline/load.py
uw_highP_geophysics_tools-0.8.1.post1.dist-info/LICENSE.txt
uw_highP_geophysics_tools-0.8.1.post1.dist-info/METADATA
uw_highP_geophysics_tools-0.8.1.post1.dist-info/WHEEL
uw_highP_geophysics_tools-0.8.1.post1.dist-info/top_level.txt
uw_highP_geophysics_tools-0.8.1.post1.dist-info/RECORD
