Metadata-Version: 2.1
Name: uw-highP-geophysics-tools
Version: 0.8.1.post1
Summary: load and evaluate splines developed in MatLab -- for Gibbs energy splines, also calculates several other thermodynamic variables for pure substances or single-solute solutions
Home-page: https://github.com/jmichaelb/LocalBasisFunction
Author: pennythewho
Author-email: pennythewho@gmail.com
License: UNKNOWN
Platform: UNKNOWN
Classifier: Programming Language :: Python :: 3.7
Classifier: License :: OSI Approved :: GNU General Public License v3 (GPLv3)
Classifier: Operating System :: OS Independent
Requires-Dist: scipy
Requires-Dist: hdf5storage
Requires-Dist: psutil
